sphinxjsondomain.py
sphinx_jsondomain-0.0.3.dist-info/DESCRIPTION.rst
sphinx_jsondomain-0.0.3.dist-info/METADATA
sphinx_jsondomain-0.0.3.dist-info/RECORD
sphinx_jsondomain-0.0.3.dist-info/WHEEL
sphinx_jsondomain-0.0.3.dist-info/metadata.json
sphinx_jsondomain-0.0.3.dist-info/top_level.txt
