Metadata-Version: 1.1
Name: sphinx-jsondomain
Version: 0.0.3
Summary: Describe JSON document structures in sphinx
Home-page: https://github.com/dave-shawley/sphinx-jsondomain
Author: Dave Shawley
Author-email: daveshawley+python@gmail.com
License: BSD
Platform: UNKNOWN
Classifier: Development Status :: 3 - Alpha
Classifier: Intended Audience :: Developers
Classifier: License :: OSI Approved :: BSD License
Classifier: Operating System :: OS Independent
Classifier: Programming Language :: Python
Classifier: Programming Language :: Python :: 2
Classifier: Programming Language :: Python :: 2.7
Classifier: Programming Language :: Python :: 3
Classifier: Programming Language :: Python :: 3.4
Classifier: Framework :: Sphinx :: Extension
